Metadata-Version: 1.0
Name: pbPlist
Version: 1.0.4
Summary: Property List Parser and Serializer. Supports XML, Binary, and NeXTSTEP Property Lists.
Home-page: https://github.com/samdmarshall/pbPlist
Author: Samantha Marshall
Author-email: hello@pewpewthespells.com
License: BSD 3-Clause
Platform: UNKNOWN
